MANIFEST.in
README.rst
setup.py
comcom/ComnameCutter.py
comcom/__init__.py
comcom/comcom.py
comcom/get_feature.py
comcom/getcomlogo.py
comcom/scope2vector.py
comcom.egg-info/PKG-INFO
comcom.egg-info/SOURCES.txt
comcom.egg-info/dependency_links.txt
comcom.egg-info/requires.txt
comcom.egg-info/top_level.txt
comcom/data/README.md
comcom/data/com_citys.dat
comcom/data/com_names5w.json
comcom/data/com_tails.dat
comcom/data/com_types.dat
comcom/data/gbt4547.json
comcom/data/gbt4547_tmpl.json
comcom/data/ignores.json
comcom/data/keywords.json
comcom/data/merges.json
comcom/data/results.json
comcom/data/scopeverbs.json
comcom/data/stop_list.json
comcom/json/com_cities.json
comcom/json/com_tails.json
comcom/json/com_types.json
comcom/rmap/rmap_代理.json
comcom/rmap/rmap_其它.json
comcom/rmap/rmap_养殖.json
comcom/rmap/rmap_制造.json
comcom/rmap/rmap_咨询.json
comcom/rmap/rmap_安装.json
comcom/rmap/rmap_工程.json
comcom/rmap/rmap_开采.json
comcom/rmap/rmap_技开.json
comcom/rmap/rmap_技推.json
comcom/rmap/rmap_技服.json
comcom/rmap/rmap_投资.json
comcom/rmap/rmap_教育.json
comcom/rmap/rmap_施工.json
comcom/rmap/rmap_服务.json
comcom/rmap/rmap_种植.json
comcom/rmap/rmap_租赁.json
comcom/rmap/rmap_管理.json
comcom/rmap/rmap_维修.json
comcom/rmap/rmap_设计.json
comcom/rmap/rmap_运输.json
comcom/rmap/rmap_采选.json
comcom/rmap/rmap_销售.json